odoo/addons/website_cookiefirst/README.rst
odoo/addons/website_cookiefirst/__init__.py
odoo/addons/website_cookiefirst/__manifest__.py
odoo/addons/website_cookiefirst/data/cookies_policy.xml
odoo/addons/website_cookiefirst/i18n/website_cookiefirst.pot
odoo/addons/website_cookiefirst/models/__init__.py
odoo/addons/website_cookiefirst/models/res_config_settings.py
odoo/addons/website_cookiefirst/models/website.py
odoo/addons/website_cookiefirst/readme/CONFIGURE.rst
odoo/addons/website_cookiefirst/readme/CONTRIBUTORS.rst
odoo/addons/website_cookiefirst/readme/DESCRIPTION.rst
odoo/addons/website_cookiefirst/static/description/icon.png
odoo/addons/website_cookiefirst/static/description/index.html
odoo/addons/website_cookiefirst/views/portal_template.xml
odoo/addons/website_cookiefirst/views/res_config_settings_views.xml
odoo13_addon_website_cookiefirst-13.0.1.1.0.dist-info/METADATA
odoo13_addon_website_cookiefirst-13.0.1.1.0.dist-info/WHEEL
odoo13_addon_website_cookiefirst-13.0.1.1.0.dist-info/top_level.txt
odoo13_addon_website_cookiefirst-13.0.1.1.0.dist-info/RECORD
